<?xml version="1.0" encoding="utf-8"?>
<!DOCTYPE xliff PUBLIC "-//XLIFF//DTD XLIFF//EN" "http://www.oasis-open.org/committees/xliff/documents/xliff.dtd">
<xliff version="1.0">
  <file source-language="EN" target-language="fr" datatype="plaintext" original="messages" date="2010-03-07T17:15:57Z" product-name="messages">
      <trans-unit id="2" xml:space="preserve">
        <source>Loading</source>
        <target>Chargement</target>
      </trans-unit>
      <trans-unit id="3" xml:space="preserve">
        <source>Sign in</source>
        <target>Se connecter</target>
      </trans-unit>
      <trans-unit id="4" xml:space="preserve">
        <source>Forgot password?</source>
        <target>Perdu son mot de passe ?</target>
      </trans-unit>
      <trans-unit id="5" xml:space="preserve">
        <source>Sign up</source>
        <target></target>
      </trans-unit>
      <trans-unit id="6" xml:space="preserve">
        <source>Hello</source>
        <target>Bonjour</target>
      </trans-unit>
      <trans-unit id="7" xml:space="preserve">
        <source>Logout</source>
        <target>Se déconnecter</target>
      </trans-unit>
      <trans-unit id="8" xml:space="preserve">
        <source>Login</source>
        <target>Se connecter</target>
      </trans-unit>
    </body>
  </file>
</xliff>
